{
	"state": "Virginia",
	"agency": "Department of Game and Inland Fisheries",
	"date_effective": "2014-07-01",
	"date_expires": "2015-06-30",
	"schema": "",
	"schema_version": "1.0a",
	"documentation": "",
	"species": {
		"name": "Redear Sunfish",
		"taxonomy": "Lepomis microlophus",
		"bova_id": 10185,
		"images": [
			{
				"name": "Redear Sunfish",
				"url": "http://www.dgif.virginia.gov/wildlife/fish/images/010185.jpg",
				"credit": "Duane Raver, U.S. Fish and Wildlife Service"
			}
		],
		"aliases": [
			"Shellcracker"
		],
		"identification": "Sunfish family. Yellow-green or olive, with faint vertical bars and random dark spots. During spawning, the margin of the male's gill cover flap turns bright red. Body is rounded like other sunfish and has a relatively small mouth.\\nPectoral fins are long and pointed. They grow faster and larger than other sunfish; 1 lb. fish not uncommon and often reaching 2 lbs."
	},
	"limits": {
		"description": "20 per day. No length limits.",
		"exceptions": {
			"1": {
				"place": "Virginia",
				"description": "See Virginia Freshwater Fishing & Watercraft Owner’s Guide for generic statewide fishing restrictions."
			}
		}
	},
	"best_fishing": {
		"description": "Lakes: Cohoon, Meade, Prince, Little Creek, Chickahominy, Robertson, Western Branch, Lone Star, and Briery Creek. Rivers: Nottoway.",
		"lakes": {
			"Cohoon": {
				"gnis_id": 1502117,
				"latitude": 36.7572092,
				"longitude": -76.645278
			},
			"Meade": {
				"gnis_id": 1479073,
				"latitude": 36.7325115,
				"longitude": -76.6075666
			},
			"Prince": {
				"gnis_id": 1502102,
				"latitude": 36.806427,
				"longitude": -76.6466867
			},
			"Little Creek": {
				"gnis_id": 1469523,
				"latitude": 37.230962,
				"longitude": -78.6051891
			},
			"Chickahominy": {
				"gnis_id": 1478078,
				"latitude": 37.4037577,
				"longitude": -76.956077
			},
			"Robertson": {
				"gnis_id": 1488819,
				"latitude": 37.8033179,
				"longitude": -79.6077461
			},
			"Western Branch": {
				"gnis_id": 1479861,
				"latitude": 36.8060143,
				"longitude": -76.6182993
			},
			"Lone Star": {
				"gnis_id": null
			},
			"Briery Creek": {
				"gnis_id": null
			}
		},
		"rivers": {
			"Nottoway": {
				"gnis_id": 1471681,
				"latitude": 36.5437634,
				"longitude": -76.9160718
			}
		}
	},
	"fishing_techniques": "Best time to catch redears is in the spring when they come up to the spawning beds. Being bottom feeders, most redears are caught by letting live nymphs, red wigglers or garden worms lie on the bottom near shore. Artificial jigs and grubs fished slowly and near the bottom will work as well."
}
